saint72/__init__.py
saint72/generator.py
saint72-0.1.0.dist-info/METADATA
saint72-0.1.0.dist-info/WHEEL
saint72-0.1.0.dist-info/top_level.txt
saint72-0.1.0.dist-info/RECORD
