Metadata-Version: 2.4
Name: saint72
Version: 0.1.0
Summary: Генератор файла с кодом в корне проекта
Author: Ваше Имя
Requires-Python: >=3.6
Dynamic: requires-python
